{
  "schemaVersion": "1.0",
  "contextRules": [
    {
      "match": {
        "contextType": "decision"
      },
      "distributions": [
        {
          "id": "decision.outcome_by_segment",
          "facetKey": "decision_outcome",
          "title": "Sentiment (buy/sell/hold)"
        },
        {
          "id": "decision.confidence_by_segment",
          "facetKey": "decision_confidence",
          "title": "Decision confidence"
        }
      ]
    },
    {
      "match": {
        "contextType": "user_feedback"
      },
      "distributions": [
        {
          "id": "user_feedback.info_sufficiency_by_segment",
          "facetKey": "information_sufficiency",
          "title": "Information sufficiency"
        }
      ]
    }
  ]
}
